LICENSE
README.md
setup.py
TANGO_Py.egg-info/PKG-INFO
TANGO_Py.egg-info/SOURCES.txt
TANGO_Py.egg-info/dependency_links.txt
TANGO_Py.egg-info/requires.txt
TANGO_Py.egg-info/top_level.txt
pytango/__init__.py
pytango/evsf/__init__.py
pytango/evsf/evsf.py
pytango/evsf/plot.py
pytango/utils/__init__.py
pytango/utils/utils.py