Metadata-Version: 2.1
Name: TANGO-Py
Version: 0.1
Summary: Tools for Analysis of Nuclear Genome Organization
Home-page: https://github.com/ARChE-MNHN/PyTANGO.git
Author: Jean Ollion
Author-email: jean.ollion@polytechnique.org
License: UNKNOWN
Download-URL: https://github.com/ARChE-MNHN/PyTANGO/archive/v_01.tar.gz
Keywords: bacmman,pandas,data analysis,TANGO,micorscopy,nuclear organization
Platform: UNKNOWN
Classifier: Development Status :: 4 - Beta
Classifier: Intended Audience :: Science/Research
Classifier: Programming Language :: Python :: 3
Classifier: License :: OSI Approved :: GNU General Public License v3 or later (GPLv3+)
Classifier: Operating System :: OS Independent
Requires-Python: >=3
License-File: LICENSE
